gistey/ArgumentParser.py
gistey/__init__.py
gistey/gistey.py
gistey-0.1.1.dist-info/DESCRIPTION.rst
gistey-0.1.1.dist-info/METADATA
gistey-0.1.1.dist-info/RECORD
gistey-0.1.1.dist-info/WHEEL
gistey-0.1.1.dist-info/entry_points.txt
gistey-0.1.1.dist-info/metadata.json
gistey-0.1.1.dist-info/top_level.txt
