Metadata-Version: 2.0
Name: gistey
Version: 0.1.1
Summary: Make GitHub gists from cmdline/terminal
Home-page: http://meetmangukiya.github.io
Author: Meet Mangukiya
Author-email: meetmangukiya98@gmail.com
License: MIT
Platform: UNKNOWN
Requires-Dist: requests (>=2.4.2)
